{"provides":{"Mouse::Meta::Method::Destructor":{"file":"Mouse/Meta/Method/Destructor.pm"},"Mouse::Meta::Attribute":{"file":"Mouse/Meta/Attribute.pm"},"Mouse::Spec":{"version":"0.97","file":"Mouse/Spec.pm"},"Test::Mouse":{"file":"Test/Mouse.pm"},"Mouse::Meta::Role::Composite":{"file":"Mouse/Meta/Role/Composite.pm"},"Mouse::PurePerl":{"file":"Mouse/PurePerl.pm"},"Squirrel":{"file":"Squirrel.pm"},"Mouse":{"version":"0.97","file":"Mouse.pm"},"Mouse::Meta::Role::Application::RoleSummation":{"file":"Mouse/Tiny.pm"},"Mouse::Object":{"file":"Mouse/Object.pm"},"Mouse::Util::MetaRole":{"file":"Mouse/Util/MetaRole.pm"},"Mouse::Meta::Method::Accessor":{"file":"Mouse/Meta/Method/Accessor.pm"},"Mouse::Meta::Class":{"file":"Mouse/Meta/Class.pm"},"Mouse::Meta::TypeConstraint":{"file":"Mouse/Meta/TypeConstraint.pm"},"Mouse::Util":{"version":"0.97","file":"Mouse/Util.pm"},"Mouse::Meta::Method":{"file":"Mouse/Meta/Method.pm"},"Mouse::Meta::Method::Delegation":{"file":"Mouse/Meta/Method/Delegation.pm"},"Mouse::Meta::Role::Application":{"file":"Mouse/Meta/Role/Application.pm"},"Mouse::Role":{"version":"0.97","file":"Mouse/Role.pm"},"Squirrel::Role":{"file":"Squirrel/Role.pm"},"Mouse::Tiny":{"version":"0.97","file":"Mouse/Tiny.pm"},"Mouse::Exporter":{"file":"Mouse/Exporter.pm"},"Mouse::Meta::Method::Constructor":{"file":"Mouse/Meta/Method/Constructor.pm"},"Mouse::Meta::Role::Method":{"file":"Mouse/Meta/Role/Method.pm"},"Mouse::Meta::Module":{"file":"Mouse/Meta/Module.pm"},"Mouse::Meta::Role":{"file":"Mouse/Meta/Role.pm"},"Mouse::TypeRegistry":{"file":"Mouse/TypeRegistry.pm"},"Mouse::Util::TypeConstraints":{"file":"Mouse/Util/TypeConstraints.pm"},"ouse":{"file":"ouse.pm"}},"target":"Mouse","version":"0.97","name":"Mouse","dist":"Mouse-0.97","pathname":"G/GF/GFUJI/Mouse-0.97.tar.gz"}